<?xml version="1.0" encoding="utf-8" ?><dwsync><file name="home-concept-dark.png" server="www.prodiisa.com//httpdocs/" local="3623426706" remote="3697758840" Dst="-1" /><file name="home-concept-item-dark.png" server="www.prodiisa.com//httpdocs/" local="3623426706" remote="3697758840" Dst="-1" /><file name="home-concept-icons-dark.png" server="www.prodiisa.com//httpdocs/" local="3623426708" remote="3697758840" Dst="-1" /><file name="home-concept.png" server="www.prodiisa.com//httpdocs/" local="3623426706" remote="3697758840" Dst="-1" /><file name="home-concept-item.png" server="www.prodiisa.com//httpdocs/" local="3623426706" remote="3697758840" Dst="-1" /><file name="home-concept-icons.png" server="www.prodiisa.com//httpdocs/" local="3623426706" remote="3697758840" Dst="-1" /><file name="home-concept-small.png" server="www.prodiisa.com//httpdocs/" local="3623426708" remote="3697758840" Dst="-1" /><file name="home-concept-item-1.png" server="www.prodiisa.com//httpdocs/" local="3623426704" remote="3697760040" Dst="-1" /><file name="home-concept-item-2.png" server="www.prodiisa.com//httpdocs/" local="3623426704" remote="3697760040" Dst="-1" /><file name="home-concept-item-3.png" server="www.prodiisa.com//httpdocs/" local="3623426704" remote="3697760040" Dst="-1" /><file name="home-concept-rtl.png" server="www.prodiisa.com//httpdocs/" local="3623426706" remote="3697760040" Dst="-1" /><file name="home-concept-small-shadow.png" server="www.prodiisa.com//httpdocs/" local="3623426708" remote="3697760040" Dst="-1" /></dwsync>